{"name": "places/ChIJWxjtZ07afkcRB8rNG2VlSrk", "id": "ChIJWxjtZ07afkcRB8rNG2VlSrk", "types": ["bar", "point_of_interest", "establishment"], "nationalPhoneNumber": "349 680 6006", "internationalPhoneNumber": "+39 349 680 6006", "formattedAddress": "Via Brigata Padova, 3, 35138 Padova PD, Italy", "addressComponents": [{"longText": "3", "shortText": "3", "types": ["street_number"], "languageCode": "en-US"}, {"longText": "Via Brigata Padova", "shortText": "Via Brigata Padova", "types": ["route"], "languageCode": "it"}, {"longText": "Padova", "shortText": "Padova", "types": ["locality", "political"], "languageCode": "it"}, {"longText": "Padova", "shortText": "Padova", "types": ["administrative_area_level_3", "political"], "languageCode": "it"}, {"longText": "Provincia di Padova", "shortText": "PD", "types": ["administrative_area_level_2", "political"], "languageCode": "it"}, {"longText": "Veneto", "shortText": "Veneto", "types": ["administrative_area_level_1", "political"], "languageCode": "it"}, {"longText": "Italy", "shortText": "IT", "types": ["country", "political"], "languageCode": "en"}, {"longText": "35138", "shortText": "35138", "types": ["postal_code"], "languageCode": "en-US"}], "plusCode": {"globalCode": "8FQHCV46+W4", "compoundCode": "CV46+W4 Padua, Province of Padua, Italy"}, "location": {"latitude": 45.407285699999996, "longitude": 11.860332099999999}, "viewport": {"low": {"latitude": 45.4059480197085, "longitude": 11.859083869708495}, "high": {"latitude": 45.40864598029149, "longitude": 11.8617818302915}}, "rating": 4.8, "googleMapsUri": "https://maps.google.com/?cid=13351595530225830407", "websiteUri": "http://www.hardcoreproduction.com/", "regularOpeningHours": {"openNow": true, "periods": [{"open": {"day": 2, "hour": 17, "minute": 0}, "close": {"day": 3, "hour": 2, "minute": 0}}, {"open": {"day": 3, "hour": 17, "minute": 0}, "close": {"day": 4, "hour": 2, "minute": 0}}, {"open": {"day": 4, "hour": 17, "minute": 0}, "close": {"day": 5, "hour": 2, "minute": 0}}, {"open": {"day": 5, "hour": 17, "minute": 0}, "close": {"day": 6, "hour": 2, "minute": 0}}, {"open": {"day": 6, "hour": 17, "minute": 0}, "close": {"day": 0, "hour": 2, "minute": 0}}], "weekdayDescriptions": ["Monday: Closed", "Tuesday: 5:00\u202fPM\u2009\u2013\u20092:00\u202fAM", "Wednesday: 5:00\u202fPM\u2009\u2013\u20092:00\u202fAM", "Thursday: 5:00\u202fPM\u2009\u2013\u20092:00\u202fAM", "Friday: 5:00\u202fPM\u2009\u2013\u20092:00\u202fAM", "Saturday: 5:00\u202fPM\u2009\u2013\u20092:00\u202fAM", "Sunday: Closed"]}, "utcOffsetMinutes": 120, "adrFormatAddress": "<span class=\"street-address\">Via Brigata Padova, 3</span>, <span class=\"postal-code\">35138</span> <span class=\"locality\">Padova</span> <span class=\"region\">PD</span>, <span class=\"country-name\">Italy</span>", "businessStatus": "OPERATIONAL", "priceLevel": "PRICE_LEVEL_MODERATE", "userRatingCount": 258, "iconMaskBaseUri": "https://maps.gstatic.com/mapfiles/place_api/icons/v2/bar_pinlet", "iconBackgroundColor": "#FF9E67", "displayName": {"text": "Caf\u00e9 Lumi\u00e8re", "languageCode": "it"}, "primaryTypeDisplayName": {"text": "Bar", "languageCode": "en-US"}, "takeout": false, "delivery": false, "dineIn": true, "reservable": true, "servesBeer": true, "servesWine": true, "currentOpeningHours": {"openNow": true, "periods": [{"open": {"day": 2, "hour": 17, "minute": 0, "date": {"year": 2024, "month": 6, "day": 4}}, "close": {"day": 3, "hour": 2, "minute": 0, "date": {"year": 2024, "month": 6, "day": 5}}}, {"open": {"day": 3, "hour": 17, "minute": 0, "date": {"year": 2024, "month": 6, "day": 5}}, "close": {"day": 4, "hour": 2, "minute": 0, "date": {"year": 2024, "month": 6, "day": 6}}}, {"open": {"day": 4, "hour": 17, "minute": 0, "date": {"year": 2024, "month": 6, "day": 6}}, "close": {"day": 5, "hour": 2, "minute": 0, "date": {"year": 2024, "month": 6, "day": 7}}}, {"open": {"day": 5, "hour": 17, "minute": 0, "date": {"year": 2024, "month": 6, "day": 7}}, "close": {"day": 5, "hour": 23, "minute": 59, "truncated": true, "date": {"year": 2024, "month": 6, "day": 7}}}, {"open": {"day": 6, "hour": 0, "minute": 0, "truncated": true, "date": {"year": 2024, "month": 6, "day": 1}}, "close": {"day": 6, "hour": 2, "minute": 0, "date": {"year": 2024, "month": 6, "day": 1}}}, {"open": {"day": 6, "hour": 17, "minute": 0, "date": {"year": 2024, "month": 6, "day": 1}}, "close": {"day": 0, "hour": 2, "minute": 0, "date": {"year": 2024, "month": 6, "day": 2}}}], "weekdayDescriptions": ["Monday: Closed", "Tuesday: 5:00\u202fPM\u2009\u2013\u20092:00\u202fAM", "Wednesday: 5:00\u202fPM\u2009\u2013\u20092:00\u202fAM", "Thursday: 5:00\u202fPM\u2009\u2013\u20092:00\u202fAM", "Friday: 5:00\u202fPM\u2009\u2013\u20092:00\u202fAM", "Saturday: 5:00\u202fPM\u2009\u2013\u20092:00\u202fAM", "Sunday: Closed"]}, "primaryType": "bar", "shortFormattedAddress": "Via Brigata Padova, 3, Padova", "reviews": [{"name": "places/ChIJWxjtZ07afkcRB8rNG2VlSrk/reviews/ChZDSUhNMG9nS0VJQ0FnSUNCNFl5ZGZ3EAE", "relativePublishTimeDescription": "a year ago", "rating": 5, "text": {"text": "Very interesting, diverse and welcoming place, with a large range of cocktails. Not so sure about all the pictures of half-naked women, though. I'm straight but, to be equal and not so sexist, surely there should be more pictures of half-naked men too? \ud83d\ude42", "languageCode": "en"}, "originalText": {"text": "Very interesting, diverse and welcoming place, with a large range of cocktails. Not so sure about all the pictures of half-naked women, though. I'm straight but, to be equal and not so sexist, surely there should be more pictures of half-naked men too? \ud83d\ude42", "languageCode": "en"}, "authorAttribution": {"displayName": "John Murphy", "uri": "https://www.google.com/maps/contrib/106203482867011452878/reviews", "photoUri": "https://lh3.googleusercontent.com/a-/ALV-UjU1WMhwmvWQ_cFx_q1FjQ5jOhw03bE8FAEeKTKBAAuh3N7T2uLR=s128-c0x00000000-cc-rp-mo-ba6"}, "publishTime": "2022-12-27T20:52:09Z"}, {"name": "places/ChIJWxjtZ07afkcRB8rNG2VlSrk/reviews/ChdDSUhNMG9nS0VJQ0FnSUQ0all6czlnRRAB", "relativePublishTimeDescription": "4 years ago", "rating": 5, "text": {"text": "Amazing cocktail place with a decadent and dark style. My favourite bar in Padua. A must for any lovers of alternative music and/or BDSM culture.", "languageCode": "en"}, "originalText": {"text": "Amazing cocktail place with a decadent and dark style. My favourite bar in Padua. A must for any lovers of alternative music and/or BDSM culture.", "languageCode": "en"}, "authorAttribution": {"displayName": "Olrac M.", "uri": "https://www.google.com/maps/contrib/109297420519462754004/reviews", "photoUri": "https://lh3.googleusercontent.com/a-/ALV-UjVCgJRfXJkIeJM81fOQQsxmN6wSOf3Hkuqyq_8y0qYGYztaGYY=s128-c0x00000000-cc-rp-mo-ba3"}, "publishTime": "2019-06-14T21:16:18Z"}, {"name": "places/ChIJWxjtZ07afkcRB8rNG2VlSrk/reviews/ChZDSUhNMG9nS0VJQ0FnSUNvMU5EbmFREAE", "relativePublishTimeDescription": "5 years ago", "rating": 5, "text": {"text": "Great cocktails, unusual atmosphere, not kind of a place to bring your grandma if you know what I mean?", "languageCode": "en"}, "originalText": {"text": "Great cocktails, unusual atmosphere, not kind of a place to bring your grandma if you know what I mean?", "languageCode": "en"}, "authorAttribution": {"displayName": "Maria Makarov", "uri": "https://www.google.com/maps/contrib/102211648791720505128/reviews", "photoUri": "https://lh3.googleusercontent.com/a-/ALV-UjWHCctHPrIZmnnOCo-OS5SLx9F7X1Xpn2gAuosPETiXngWvEa_nXA=s128-c0x00000000-cc-rp-mo-ba3"}, "publishTime": "2019-02-06T09:13:13Z"}, {"name": "places/ChIJWxjtZ07afkcRB8rNG2VlSrk/reviews/ChZDSUhNMG9nS0VJQ0FnSUQ2bzZPalhREAE", "relativePublishTimeDescription": "2 years ago", "rating": 5, "text": {"text": "Cool place, very good cocktail variety", "languageCode": "en"}, "originalText": {"text": "Cool place, very good cocktail variety", "languageCode": "en"}, "authorAttribution": {"displayName": "Alexandru Ciprian Ciuca", "uri": "https://www.google.com/maps/contrib/111233932492910319028/reviews", "photoUri": "https://lh3.googleusercontent.com/a-/ALV-UjV7XYu3QVmBYw7ss3x_m92jQcaieMIT356UJCqWoz1fU_pcYLE=s128-c0x00000000-cc-rp-mo"}, "publishTime": "2021-10-09T20:23:50Z"}, {"name": "places/ChIJWxjtZ07afkcRB8rNG2VlSrk/reviews/ChZDSUhNMG9nS0VJQ0FnSURqdDV2WFBnEAE", "relativePublishTimeDescription": "3 weeks ago", "rating": 5, "text": {"text": "Delicious!", "languageCode": "en"}, "originalText": {"text": "Delicious!", "languageCode": "en"}, "authorAttribution": {"displayName": "Laise Polonio", "uri": "https://www.google.com/maps/contrib/114800889226531846495/reviews", "photoUri": "https://lh3.googleusercontent.com/a-/ALV-UjURaFRkqoXDY0CwJdYanz9uIDYnEIKT7uUkOE2_ZbNVREsCLGHC8g=s128-c0x00000000-cc-rp-mo-ba4"}, "publishTime": "2024-05-08T17:23:29Z"}], "photos": [{"name": "places/ChIJWxjtZ07afkcRB8rNG2VlSrk/photos/AUGGfZm-6Rzg7Cz7r9m2h7cTuEcBIwCWLjaN7Bt4Fh1RuUPUInCmzZo3c-f9U4-Ij5MKnaem7Vm7aofIKI-mlbJXgEc5ttkhc0omZYtGub2zxF-aoUs8AKUbV-0Gro6GdVqb_rYvxcvSclAhb7BQUeFCswfDZG68XPr9rCnh", "widthPx": 5712, "heightPx": 4284, "authorAttributions": [{"displayName": "Andrea D", "uri": "//maps.google.com/maps/contrib/114006267137100278400", "photoUri": "//lh3.googleusercontent.com/a/ACg8ocJq1svGpsH_v9AN0yqDtYIg91IaaYc6I0xW0vrEnbZ7SvY_kA=s100-p-k-no-mo"}]}, {"name": "places/ChIJWxjtZ07afkcRB8rNG2VlSrk/photos/AUGGfZmEB24igZVRB1SBmOaeGgUqDJLVBIUJFwe-6jEBamCLilqAC2aCWcU-gMemooHU04y9tY1W68TT56sHdoM9nNBe_-pwQpGei6YGNcsF7ISIN5sO6rGcEhZfDQ5NdR7BmwLVjbGnGPOnMPy-nJYXeC35otRRN5MZ7JVB", "widthPx": 1080, "heightPx": 1350, "authorAttributions": [{"displayName": "Caf\u00e9 Lumi\u00e8re", "uri": "//maps.google.com/maps/contrib/111912544565064064157", "photoUri": "//lh3.googleusercontent.com/a/ACg8ocKB90t3lCVXXyCrIzX5fAzmedrT2SC6eH52RlI9LAB-h7orHg=s100-p-k-no-mo"}]}, {"name": "places/ChIJWxjtZ07afkcRB8rNG2VlSrk/photos/AUGGfZk3-OChmHoFyKXked_NOc-Lb2OrAL0wY9HVaBKnikgx1E11pB99x4ru33PFzBbz2G8KzlDJrE5gStY6PHqp49UoawWKl0Lslnggd4_Q76IZKz-0hIrd5iUWSBk8rwqS4Qar4UwJp03KBmdngoFPgqF2cCw3O3O7_f-a", "widthPx": 4000, "heightPx": 2250, "authorAttributions": [{"displayName": "Giada Filippo", "uri": "//maps.google.com/maps/contrib/105362133663786448486", "photoUri": "//lh3.googleusercontent.com/a-/ALV-UjUDYDTDfLE0LYbUdiW4Eh2cC10O3yCNzlMpFYMjKezDwjbfxYKV3g=s100-p-k-no-mo"}]}, {"name": "places/ChIJWxjtZ07afkcRB8rNG2VlSrk/photos/AUGGfZlRusoSZcvi8WM_ezPZi9Pw41XL1-7VsMKi0CDFRaV1RwQ8WbS5h3v1j6lL5_ulZ0Tep8QrXBQbXY_a9kFhLaICQirF2_su1StVJKFT9uRWgRFCSGF-AHu0zul5dh5qevNUNahr3J1kQAYNHR-_uqiSc-3QPrp3MsZ3", "widthPx": 1920, "heightPx": 1080, "authorAttributions": [{"displayName": "Stefan Pantu", "uri": "//maps.google.com/maps/contrib/101302022609528850672", "photoUri": "//lh3.googleusercontent.com/a/ACg8ocIaqEvHAEYxMGRXdtnPNWP0FzEGgoXw1VUSrVZLvq30uJ5QHA=s100-p-k-no-mo"}]}, {"name": "places/ChIJWxjtZ07afkcRB8rNG2VlSrk/photos/AUGGfZk50eE79f5CsTxdMvt6hNJrmAOalCnpgrZX0lN87DG5DVa4T2jzQh_KkTxD5N01djEcnVboEg2C-Va5eKM2rMwBOYbi9pnAdzbQvSQJ6TIfn-eHYVF40R9qWFQDPZZjBL9Cbl7msCTYhwJ08ipH9iWRajYxAwDfLipV", "widthPx": 720, "heightPx": 720, "authorAttributions": [{"displayName": "dario dorio", "uri": "//maps.google.com/maps/contrib/114419144261662626445", "photoUri": "//lh3.googleusercontent.com/a/ACg8ocJnOoayBS8YcDk9g9xE6ovdvBDkAyjuDly3ypB28ADz3FzZ7w=s100-p-k-no-mo"}]}, {"name": "places/ChIJWxjtZ07afkcRB8rNG2VlSrk/photos/AUGGfZlReHW_f3-YqdLAnqcsQxI0MpvVGhfpqqg2QmHOLAoPD1XHbnl_xR7hCuYM44nORuYfuRehLBfoksvMg4DQBdycRb8gHO83v0goh85nx1dSwfTfWUgaMnqbsYOyqyDSESm6P31JCtnBdLPQZAXutNqPDe9u_q0TBnUg", "widthPx": 960, "heightPx": 960, "authorAttributions": [{"displayName": "dario dorio", "uri": "//maps.google.com/maps/contrib/114419144261662626445", "photoUri": "//lh3.googleusercontent.com/a/ACg8ocJnOoayBS8YcDk9g9xE6ovdvBDkAyjuDly3ypB28ADz3FzZ7w=s100-p-k-no-mo"}]}, {"name": "places/ChIJWxjtZ07afkcRB8rNG2VlSrk/photos/AUGGfZmodvzUtTYBmIH4Kv8zOI8rCZLOpHFV0P5tTl12Z3Zmq1Nzp6ZKw8vyV3YEu4ucsgZHbWt5T8c-nO0uia42phMf3D3MEziXc3cgIF-7Fd2TAGhLa40W30TDryIcVO_rA-zwXWlWEI2XzRc1VpATbQUGft8kA2djEu0Z", "widthPx": 960, "heightPx": 472, "authorAttributions": [{"displayName": "dario dorio", "uri": "//maps.google.com/maps/contrib/114419144261662626445", "photoUri": "//lh3.googleusercontent.com/a/ACg8ocJnOoayBS8YcDk9g9xE6ovdvBDkAyjuDly3ypB28ADz3FzZ7w=s100-p-k-no-mo"}]}, {"name": "places/ChIJWxjtZ07afkcRB8rNG2VlSrk/photos/AUGGfZliuTAEbf3A2wPajGeJ92tgR4kZCDRk6rTfD0hoPbPPCHAVWQ2jZef5pmZq8txQgX3UpqRiqXKfe3VlcfLvpsL-i75ducExpqJi9vlkJgVxZrQ56MfEVl5mAcgtW0qi-z2TbWdhuvzO3XDeICJkLbq7_aDWheV-W_VS", "widthPx": 1920, "heightPx": 1080, "authorAttributions": [{"displayName": "Stefan Pantu", "uri": "//maps.google.com/maps/contrib/101302022609528850672", "photoUri": "//lh3.googleusercontent.com/a/ACg8ocIaqEvHAEYxMGRXdtnPNWP0FzEGgoXw1VUSrVZLvq30uJ5QHA=s100-p-k-no-mo"}]}, {"name": "places/ChIJWxjtZ07afkcRB8rNG2VlSrk/photos/AUGGfZm2Xkn3w2O3fLML9e0_WNcWYcHBbr_KbM7P1lxKDEKm6_dTNDZngWg6hUXzesi1AacUY_CuW7LJA5sRQGsJ6ScIGMkr2gDB6BI7aVioFVtfR3V1OMfritGjZhggZf1yLl1ArVhcZZCdA-IRti6Mr2stBM0g2-HcqiH7", "widthPx": 1920, "heightPx": 1080, "authorAttributions": [{"displayName": "Stefan Pantu", "uri": "//maps.google.com/maps/contrib/101302022609528850672", "photoUri": "//lh3.googleusercontent.com/a/ACg8ocIaqEvHAEYxMGRXdtnPNWP0FzEGgoXw1VUSrVZLvq30uJ5QHA=s100-p-k-no-mo"}]}, {"name": "places/ChIJWxjtZ07afkcRB8rNG2VlSrk/photos/AUGGfZk3mm5JJqCEqHxwX-70iygwxXNkzvcI8t91Ls7mI-Ykc6NdfgwG138z-ElRFXAybjr-vQgwEjaAihrZI2r4946jQgYDdacdlh08nwqgv2z46hi6gdTUSETynIewXjGJ_QoQdZ5e6oJE0tvf9S-XnNeWTylalhQ9xtvO", "widthPx": 2048, "heightPx": 2040, "authorAttributions": [{"displayName": "dario dorio", "uri": "//maps.google.com/maps/contrib/114419144261662626445", "photoUri": "//lh3.googleusercontent.com/a/ACg8ocJnOoayBS8YcDk9g9xE6ovdvBDkAyjuDly3ypB28ADz3FzZ7w=s100-p-k-no-mo"}]}], "outdoorSeating": false, "liveMusic": false, "servesCocktails": true, "allowsDogs": true, "restroom": true, "goodForGroups": true, "goodForWatchingSports": false, "paymentOptions": {"acceptsCreditCards": true, "acceptsDebitCards": true, "acceptsCashOnly": false, "acceptsNfc": true}, "parkingOptions": {"freeStreetParking": true}, "accessibilityOptions": {"wheelchairAccessibleEntrance": true, "wheelchairAccessibleRestroom": true}}