{"name": "places/ChIJp9DnYO3afkcRNahMnk2KUI4", "id": "ChIJp9DnYO3afkcRNahMnk2KUI4", "types": ["bar", "point_of_interest", "establishment"], "formattedAddress": "Via Antonio Grassi, 35131 Padova PD, Italy", "addressComponents": [{"longText": "Via Antonio Grassi", "shortText": "Via Antonio Grassi", "types": ["route"], "languageCode": "it"}, {"longText": "Padova", "shortText": "Padova", "types": ["locality", "political"], "languageCode": "it"}, {"longText": "Padova", "shortText": "Padova", "types": ["administrative_area_level_3", "political"], "languageCode": "it"}, {"longText": "Provincia di Padova", "shortText": "PD", "types": ["administrative_area_level_2", "political"], "languageCode": "it"}, {"longText": "Veneto", "shortText": "Veneto", "types": ["administrative_area_level_1", "political"], "languageCode": "it"}, {"longText": "Italy", "shortText": "IT", "types": ["country", "political"], "languageCode": "en"}, {"longText": "35131", "shortText": "35131", "types": ["postal_code"], "languageCode": "en-US"}], "plusCode": {"globalCode": "8FQHCW72+9X", "compoundCode": "CW72+9X Padua, Province of Padua, Italy"}, "location": {"latitude": 45.413487599999996, "longitude": 11.902415}, "viewport": {"low": {"latitude": 45.412113269708506, "longitude": 11.901149969708499}, "high": {"latitude": 45.414811230291505, "longitude": 11.903847930291503}}, "rating": 4, "googleMapsUri": "https://maps.google.com/?cid=10254848417495558197", "regularOpeningHours": {"openNow": true, "periods": [{"open": {"day": 0, "hour": 6, "minute": 0}, "close": {"day": 0, "hour": 20, "minute": 0}}, {"open": {"day": 1, "hour": 6, "minute": 0}, "close": {"day": 1, "hour": 20, "minute": 0}}, {"open": {"day": 2, "hour": 6, "minute": 0}, "close": {"day": 2, "hour": 20, "minute": 0}}, {"open": {"day": 3, "hour": 6, "minute": 0}, "close": {"day": 3, "hour": 20, "minute": 0}}, {"open": {"day": 4, "hour": 6, "minute": 0}, "close": {"day": 4, "hour": 20, "minute": 0}}, {"open": {"day": 5, "hour": 6, "minute": 0}, "close": {"day": 5, "hour": 20, "minute": 0}}, {"open": {"day": 6, "hour": 6, "minute": 0}, "close": {"day": 6, "hour": 20, "minute": 0}}], "weekdayDescriptions": ["Monday: 6:00\u202fAM\u2009\u2013\u20098:00\u202fPM", "Tuesday: 6:00\u202fAM\u2009\u2013\u20098:00\u202fPM", "Wednesday: 6:00\u202fAM\u2009\u2013\u20098:00\u202fPM", "Thursday: 6:00\u202fAM\u2009\u2013\u20098:00\u202fPM", "Friday: 6:00\u202fAM\u2009\u2013\u20098:00\u202fPM", "Saturday: 6:00\u202fAM\u2009\u2013\u20098:00\u202fPM", "Sunday: 6:00\u202fAM\u2009\u2013\u20098:00\u202fPM"]}, "utcOffsetMinutes": 120, "adrFormatAddress": "<span class=\"street-address\">Via Antonio Grassi</span>, <span class=\"postal-code\">35131</span> <span class=\"locality\">Padova</span> <span class=\"region\">PD</span>, <span class=\"country-name\">Italy</span>", "businessStatus": "OPERATIONAL", "priceLevel": "PRICE_LEVEL_INEXPENSIVE", "userRatingCount": 76, "iconMaskBaseUri": "https://maps.gstatic.com/mapfiles/place_api/icons/v2/bar_pinlet", "iconBackgroundColor": "#FF9E67", "displayName": {"text": "Bar Innocenti Evasioni", "languageCode": "it"}, "primaryTypeDisplayName": {"text": "Bar", "languageCode": "en-US"}, "dineIn": true, "servesBeer": true, "servesWine": true, "currentOpeningHours": {"openNow": true, "periods": [{"open": {"day": 0, "hour": 6, "minute": 0, "date": {"year": 2024, "month": 6, "day": 2}}, "close": {"day": 0, "hour": 20, "minute": 0, "date": {"year": 2024, "month": 6, "day": 2}}}, {"open": {"day": 1, "hour": 6, "minute": 0, "date": {"year": 2024, "month": 6, "day": 3}}, "close": {"day": 1, "hour": 20, "minute": 0, "date": {"year": 2024, "month": 6, "day": 3}}}, {"open": {"day": 2, "hour": 6, "minute": 0, "date": {"year": 2024, "month": 6, "day": 4}}, "close": {"day": 2, "hour": 20, "minute": 0, "date": {"year": 2024, "month": 6, "day": 4}}}, {"open": {"day": 3, "hour": 6, "minute": 0, "date": {"year": 2024, "month": 6, "day": 5}}, "close": {"day": 3, "hour": 20, "minute": 0, "date": {"year": 2024, "month": 6, "day": 5}}}, {"open": {"day": 4, "hour": 6, "minute": 0, "date": {"year": 2024, "month": 6, "day": 6}}, "close": {"day": 4, "hour": 20, "minute": 0, "date": {"year": 2024, "month": 6, "day": 6}}}, {"open": {"day": 5, "hour": 6, "minute": 0, "date": {"year": 2024, "month": 6, "day": 7}}, "close": {"day": 5, "hour": 20, "minute": 0, "date": {"year": 2024, "month": 6, "day": 7}}}, {"open": {"day": 6, "hour": 6, "minute": 0, "date": {"year": 2024, "month": 6, "day": 1}}, "close": {"day": 6, "hour": 20, "minute": 0, "date": {"year": 2024, "month": 6, "day": 1}}}], "weekdayDescriptions": ["Monday: 6:00\u202fAM\u2009\u2013\u20098:00\u202fPM", "Tuesday: 6:00\u202fAM\u2009\u2013\u20098:00\u202fPM", "Wednesday: 6:00\u202fAM\u2009\u2013\u20098:00\u202fPM", "Thursday: 6:00\u202fAM\u2009\u2013\u20098:00\u202fPM", "Friday: 6:00\u202fAM\u2009\u2013\u20098:00\u202fPM", "Saturday: 6:00\u202fAM\u2009\u2013\u20098:00\u202fPM", "Sunday: 6:00\u202fAM\u2009\u2013\u20098:00\u202fPM"]}, "primaryType": "bar", "shortFormattedAddress": "Via Antonio Grassi, Padova", "reviews": [{"name": "places/ChIJp9DnYO3afkcRNahMnk2KUI4/reviews/ChdDSUhNMG9nS0VJQ0FnSUNacTViOXBRRRAB", "relativePublishTimeDescription": "8 months ago", "rating": 4, "text": {"text": "Good choice of drinks and decent choice of sandwiches, good coffee, fast and courteous service, excellent hygiene and clean bathroom", "languageCode": "en-US"}, "originalText": {"text": "Buona scelta di bevande  e discreta  scelta di tramezzini , buon  caff\u00e8, servizio  veloce   e   cortesia  ,  ottima  igiene  e  bagno  pulito", "languageCode": "it"}, "authorAttribution": {"displayName": "ANTONIO FERRERO", "uri": "https://www.google.com/maps/contrib/113433352883783006339/reviews", "photoUri": "https://lh3.googleusercontent.com/a/ACg8ocLa0Y5KZALVhIn5JcrpTBz3XSQovvNNby5_iDYP5Kn11lD4rA=s128-c0x00000000-cc-rp-mo-ba3"}, "publishTime": "2023-09-18T10:49:53Z"}, {"name": "places/ChIJp9DnYO3afkcRNahMnk2KUI4/reviews/ChdDSUhNMG9nS0VJQ0FnSUQwOFBTQzFnRRAB", "relativePublishTimeDescription": "4 years ago", "rating": 5, "text": {"text": "Poorly managed and poorly frequented bar, always full of unsavory people.\nHowever, it is the perfect place for an evening march. Bottles of decent red for \u20ac6 and entry level white Maculan (excellent winery from Breganze) for \u20ac7, so very honest.\nWe went in one evening a few months ago asking what time it closed, and we were told \"when you leave\". If this isn't true hospitality!\nEventually we met a drunk middle-aged lady, with whom we sang the rumatera at the top of our lungs. The owner gave the lady the brioches left over from the day, and shared them with us. Pure poetry.\nIn conclusion: clear and beautiful example of multiculturalism and integration among poor people.", "languageCode": "en-US"}, "originalText": {"text": "Bar mal gestito e mal frequentato, sempre pieno di gente poco raccomandabile.\nTuttavia \u00e8 il posto perfetto per fare serata marcia. Bottiglie di rosso dignitoso a 6\u20ac e di bianco entry level Maculan (ottima cantina di Breganze) a 7\u20ac, per cui onestissimo.\nSiamo entrati una sera alcuni mesi fa chiedendo a che ora chiudesse, e ci \u00e8 stato risposto \"quando andrete via voi\". Se non \u00e8 vera accoglienza questa!\nAlla fine abbiamo fatto conoscenza con una signora di mezz'et\u00e0 ubriaca, con cui abbiamo cantato i rumatera a squarciagola. Il titolare ha regalato alla signora le brioches avanzate dalla giornata, e le ha condivise con noi. Poesia pura.\nIn conclusione: chiaro e bellissimo esempio di multiculturalismo e integrazione fra povera gente.", "languageCode": "it"}, "authorAttribution": {"displayName": "Paolo Artuso", "uri": "https://www.google.com/maps/contrib/101992227943994597634/reviews", "photoUri": "https://lh3.googleusercontent.com/a/ACg8ocKElcHJwDwu7V7JOSABjCDp2ITrywLtURLucjQ-pdmNoPyR66kd=s128-c0x00000000-cc-rp-mo-ba3"}, "publishTime": "2019-10-19T17:13:55Z"}, {"name": "places/ChIJp9DnYO3afkcRNahMnk2KUI4/reviews/ChdDSUhNMG9nS0VJQ0FnSURRMW9lLTRRRRAB", "relativePublishTimeDescription": "6 years ago", "rating": 5, "text": {"text": "Pure, adorable trash. The place is a poorly frequented dive, it smells old and is located in an awkward position facing the street and is run by Chinese who 90% of the time won't understand what you ordered. Staff empathy rating: 0.1 out of 10.\nIt is so powerful that all of this, inexplicably, conquers you with virulent impetus. And you find yourself there every time you pass by it, until little by little... it becomes your second home.\nThe cosmopolitan and multicultural attitude of the patrons triumphs in a riot of beer, swearing, gambling addiction and cigarettes. Here every customer is truly your neighbor, with whom you can share a shadow or talk about cosmic nothingness\n\nPS: large summer garden caged by a protective net - a masterpiece of 70s brutalist architecture.", "languageCode": "en-US"}, "originalText": {"text": "Puro, adorabile trash. Il posto \u00e8 un baraccio mal frequentato, puzza di vecchio e si trova in una posizione scomoda fronte strada ed \u00e8 gestito da cinesi che al 90% non comprenderanno cos\u2019hai ordinato. Grado di empatia dello staff: 0.1 su 10.\nFa talmente poranza che tutto ci\u00f3, inspiegabilmente, ti conquista con impeto virulento. E ti ritrovi l\u00ec ogni volta che ci passi davanti, finch\u00e9 piano piano... diventa la tua seconda casa.\nL\u2019attitudine cosmopolita e multiculturale degli avventori trionfa in un tripudio di birra, bestemmie, ludopatia e sigarette. Qui ogni avventore \u00e8 davvero il tuo prossimo, con cui condividere un\u2019ombra o parlare del nulla cosmico\n\nPs: ampio giardino estivo ingabbiato da rete di protezione - capolavoro dell\u2019architettura brutalista anni 70.", "languageCode": "it"}, "authorAttribution": {"displayName": "Francesca Valente", "uri": "https://www.google.com/maps/contrib/105976066205532286846/reviews", "photoUri": "https://lh3.googleusercontent.com/a-/ALV-UjXAW-N0a_dZV4iF9ag2-IM_m6viqyy9S6XgBP0AAd6TFyShg17A=s128-c0x00000000-cc-rp-mo"}, "publishTime": "2018-01-28T11:50:35Z"}, {"name": "places/ChIJp9DnYO3afkcRNahMnk2KUI4/reviews/ChZDSUhNMG9nS0VJQ0FnSUNxaXNMcGRBEAE", "relativePublishTimeDescription": "3 years ago", "rating": 5, "text": {"text": "A bar, a house, a place where in our youth 1976-1983, it was the haven of tranquility of rest for the bus waiter. It was our family. Greetings from Giorgio of Thessaloniki.", "languageCode": "en-US"}, "originalText": {"text": "Un bar, una casa, un posto dove nella nostra gioventu 1976-1983, e stato il  porto di tranquilita del riposo del ateso del autobus.Era la nostra famiglia. Salutti da Giorgio di Salonicco.", "languageCode": "it"}, "authorAttribution": {"displayName": "\u0393\u03b9\u03ce\u03c1\u03b3\u03bf\u03c2 \u039a.", "uri": "https://www.google.com/maps/contrib/112366392682065199433/reviews", "photoUri": "https://lh3.googleusercontent.com/a/ACg8ocIrhxAsOU_rBapzQkYQnlBaAalRhZnf53M9gMe41Zlx2m9yCw=s128-c0x00000000-cc-rp-mo"}, "publishTime": "2021-06-02T11:27:17Z"}, {"name": "places/ChIJp9DnYO3afkcRNahMnk2KUI4/reviews/ChdDSUhNMG9nS0VJQ0FnSURodXRyQV9RRRAB", "relativePublishTimeDescription": "a year ago", "rating": 2, "text": {"text": "Neighborhood bar with usual customers. I don't know but, it seems like little cleaning... closed environment", "languageCode": "en-US"}, "originalText": {"text": "Bar di quartiere con soliti clienti.non lo so ma,sembra poca pulizie... ambiente chiuso", "languageCode": "it"}, "authorAttribution": {"displayName": "Lucica Baban", "uri": "https://www.google.com/maps/contrib/102170316653056911568/reviews", "photoUri": "https://lh3.googleusercontent.com/a/ACg8ocKvs2hvr_2tt4Ta4m9faj-xPhsE51Ss1efsXjthB1T2BZrLXA=s128-c0x00000000-cc-rp-mo-ba4"}, "publishTime": "2023-03-06T23:34:45Z"}], "photos": [{"name": "places/ChIJp9DnYO3afkcRNahMnk2KUI4/photos/AUGGfZncLIMpOBbrSi4x3BI5SuBsESEhomv2zxF35Xeg0dziXO5jq3QtBhizeI2EwUWvTmTPNYYdhxqIk_TArnDgHN9RBP7FL6N9zm6XBKOfShI31HcDoO8lO1-sYSw6PQELL7ZE6cCWbvEWj7Vtp9QL13gZFQ51a2l65M8S", "widthPx": 4618, "heightPx": 3464, "authorAttributions": [{"displayName": "Giovanni Antonio Stellato", "uri": "//maps.google.com/maps/contrib/113426039307848400482", "photoUri": "//lh3.googleusercontent.com/a-/ALV-UjUDLjdY4w75xPr-3bjyqJy0OGEfkICJ_0wEAQ4kwjG8A8xvk_I5TQ=s100-p-k-no-mo"}]}], "outdoorSeating": true, "liveMusic": false, "servesCocktails": true, "allowsDogs": true, "restroom": true, "paymentOptions": {"acceptsDebitCards": true, "acceptsCashOnly": false, "acceptsNfc": true}, "accessibilityOptions": {"wheelchairAccessibleParking": true, "wheelchairAccessibleEntrance": true}}