{"name": "places/ChIJewn6MAzQfkcRTieeKzsX_Oo", "id": "ChIJewn6MAzQfkcRTieeKzsX_Oo", "types": ["restaurant", "pizza_restaurant", "italian_restaurant", "food", "point_of_interest", "establishment"], "nationalPhoneNumber": "049 703688", "internationalPhoneNumber": "+39 049 703688", "formattedAddress": "Via G. Garibaldi, 51, 35010 Cadoneghe PD, Italy", "addressComponents": [{"longText": "51", "shortText": "51", "types": ["street_number"], "languageCode": "en-US"}, {"longText": "Via G. Garibaldi", "shortText": "Via G. Garibaldi", "types": ["route"], "languageCode": "it"}, {"longText": "Cadoneghe", "shortText": "Cadoneghe", "types": ["locality", "political"], "languageCode": "it"}, {"longText": "Cadoneghe", "shortText": "Cadoneghe", "types": ["administrative_area_level_3", "political"], "languageCode": "it"}, {"longText": "Provincia di Padova", "shortText": "PD", "types": ["administrative_area_level_2", "political"], "languageCode": "it"}, {"longText": "Veneto", "shortText": "Veneto", "types": ["administrative_area_level_1", "political"], "languageCode": "it"}, {"longText": "Italy", "shortText": "IT", "types": ["country", "political"], "languageCode": "en"}, {"longText": "35010", "shortText": "35010", "types": ["postal_code"], "languageCode": "en-US"}], "plusCode": {"globalCode": "8FQHCWQH+5W", "compoundCode": "CWQH+5W Cadoneghe, Province of Padua, Italy"}, "location": {"latitude": 45.4379172, "longitude": 11.929763699999999}, "viewport": {"low": {"latitude": 45.436451669708504, "longitude": 11.928426219708497}, "high": {"latitude": 45.439149630291496, "longitude": 11.931124180291501}}, "rating": 3.9, "googleMapsUri": "https://maps.google.com/?cid=16932434241908516686", "regularOpeningHours": {"openNow": true, "periods": [{"open": {"day": 0, "hour": 11, "minute": 30}, "close": {"day": 0, "hour": 15, "minute": 30}}, {"open": {"day": 0, "hour": 18, "minute": 0}, "close": {"day": 1, "hour": 0, "minute": 0}}, {"open": {"day": 1, "hour": 11, "minute": 0}, "close": {"day": 1, "hour": 15, "minute": 0}}, {"open": {"day": 2, "hour": 11, "minute": 30}, "close": {"day": 2, "hour": 14, "minute": 30}}, {"open": {"day": 2, "hour": 18, "minute": 0}, "close": {"day": 3, "hour": 0, "minute": 0}}, {"open": {"day": 3, "hour": 11, "minute": 30}, "close": {"day": 3, "hour": 14, "minute": 30}}, {"open": {"day": 3, "hour": 18, "minute": 0}, "close": {"day": 4, "hour": 0, "minute": 0}}, {"open": {"day": 4, "hour": 11, "minute": 30}, "close": {"day": 4, "hour": 14, "minute": 30}}, {"open": {"day": 4, "hour": 18, "minute": 0}, "close": {"day": 5, "hour": 0, "minute": 0}}, {"open": {"day": 5, "hour": 11, "minute": 30}, "close": {"day": 5, "hour": 14, "minute": 30}}, {"open": {"day": 5, "hour": 18, "minute": 0}, "close": {"day": 6, "hour": 0, "minute": 0}}, {"open": {"day": 6, "hour": 18, "minute": 0}, "close": {"day": 0, "hour": 0, "minute": 0}}], "weekdayDescriptions": ["Monday: 11:00\u202fAM\u2009\u2013\u20093:00\u202fPM", "Tuesday: 11:30\u202fAM\u2009\u2013\u20092:30\u202fPM, 6:00\u202fPM\u2009\u2013\u200912:00\u202fAM", "Wednesday: 11:30\u202fAM\u2009\u2013\u20092:30\u202fPM, 6:00\u202fPM\u2009\u2013\u200912:00\u202fAM", "Thursday: 11:30\u202fAM\u2009\u2013\u20092:30\u202fPM, 6:00\u202fPM\u2009\u2013\u200912:00\u202fAM", "Friday: 11:30\u202fAM\u2009\u2013\u20092:30\u202fPM, 6:00\u202fPM\u2009\u2013\u200912:00\u202fAM", "Saturday: 6:00\u202fPM\u2009\u2013\u200912:00\u202fAM", "Sunday: 11:30\u202fAM\u2009\u2013\u20093:30\u202fPM, 6:00\u202fPM\u2009\u2013\u200912:00\u202fAM"]}, "utcOffsetMinutes": 120, "adrFormatAddress": "<span class=\"street-address\">Via G. Garibaldi, 51</span>, <span class=\"postal-code\">35010</span> <span class=\"locality\">Cadoneghe</span> <span class=\"region\">PD</span>, <span class=\"country-name\">Italy</span>", "businessStatus": "OPERATIONAL", "userRatingCount": 174, "iconMaskBaseUri": "https://maps.gstatic.com/mapfiles/place_api/icons/v2/restaurant_pinlet", "iconBackgroundColor": "#FF9E67", "displayName": {"text": "Giramondo", "languageCode": "it"}, "primaryTypeDisplayName": {"text": "Restaurant", "languageCode": "en-US"}, "takeout": true, "delivery": true, "dineIn": true, "reservable": true, "servesLunch": true, "servesDinner": true, "servesBeer": true, "servesWine": true, "servesVegetarianFood": true, "currentOpeningHours": {"openNow": true, "periods": [{"open": {"day": 0, "hour": 11, "minute": 30, "date": {"year": 2024, "month": 6, "day": 2}}, "close": {"day": 0, "hour": 15, "minute": 30, "date": {"year": 2024, "month": 6, "day": 2}}}, {"open": {"day": 0, "hour": 18, "minute": 0, "date": {"year": 2024, "month": 6, "day": 2}}, "close": {"day": 1, "hour": 0, "minute": 0, "date": {"year": 2024, "month": 6, "day": 3}}}, {"open": {"day": 1, "hour": 11, "minute": 0, "date": {"year": 2024, "month": 6, "day": 3}}, "close": {"day": 1, "hour": 15, "minute": 0, "date": {"year": 2024, "month": 6, "day": 3}}}, {"open": {"day": 2, "hour": 11, "minute": 30, "date": {"year": 2024, "month": 6, "day": 4}}, "close": {"day": 2, "hour": 14, "minute": 30, "date": {"year": 2024, "month": 6, "day": 4}}}, {"open": {"day": 2, "hour": 18, "minute": 0, "date": {"year": 2024, "month": 6, "day": 4}}, "close": {"day": 3, "hour": 0, "minute": 0, "date": {"year": 2024, "month": 6, "day": 5}}}, {"open": {"day": 3, "hour": 11, "minute": 30, "date": {"year": 2024, "month": 6, "day": 5}}, "close": {"day": 3, "hour": 14, "minute": 30, "date": {"year": 2024, "month": 6, "day": 5}}}, {"open": {"day": 3, "hour": 18, "minute": 0, "date": {"year": 2024, "month": 6, "day": 5}}, "close": {"day": 4, "hour": 0, "minute": 0, "date": {"year": 2024, "month": 6, "day": 6}}}, {"open": {"day": 4, "hour": 11, "minute": 30, "date": {"year": 2024, "month": 6, "day": 6}}, "close": {"day": 4, "hour": 14, "minute": 30, "date": {"year": 2024, "month": 6, "day": 6}}}, {"open": {"day": 4, "hour": 18, "minute": 0, "date": {"year": 2024, "month": 6, "day": 6}}, "close": {"day": 5, "hour": 0, "minute": 0, "date": {"year": 2024, "month": 6, "day": 7}}}, {"open": {"day": 5, "hour": 11, "minute": 30, "date": {"year": 2024, "month": 6, "day": 7}}, "close": {"day": 5, "hour": 14, "minute": 30, "date": {"year": 2024, "month": 6, "day": 7}}}, {"open": {"day": 5, "hour": 18, "minute": 0, "date": {"year": 2024, "month": 6, "day": 7}}, "close": {"day": 5, "hour": 23, "minute": 59, "truncated": true, "date": {"year": 2024, "month": 6, "day": 7}}}, {"open": {"day": 6, "hour": 18, "minute": 0, "date": {"year": 2024, "month": 6, "day": 1}}, "close": {"day": 0, "hour": 0, "minute": 0, "date": {"year": 2024, "month": 6, "day": 2}}}], "weekdayDescriptions": ["Monday: 11:00\u202fAM\u2009\u2013\u20093:00\u202fPM", "Tuesday: 11:30\u202fAM\u2009\u2013\u20092:30\u202fPM, 6:00\u202fPM\u2009\u2013\u200912:00\u202fAM", "Wednesday: 11:30\u202fAM\u2009\u2013\u20092:30\u202fPM, 6:00\u202fPM\u2009\u2013\u200912:00\u202fAM", "Thursday: 11:30\u202fAM\u2009\u2013\u20092:30\u202fPM, 6:00\u202fPM\u2009\u2013\u200912:00\u202fAM", "Friday: 11:30\u202fAM\u2009\u2013\u20092:30\u202fPM, 6:00\u202fPM\u2009\u2013\u200912:00\u202fAM", "Saturday: 6:00\u202fPM\u2009\u2013\u200912:00\u202fAM", "Sunday: 11:30\u202fAM\u2009\u2013\u20093:30\u202fPM, 6:00\u202fPM\u2009\u2013\u200912:00\u202fAM"]}, "primaryType": "restaurant", "shortFormattedAddress": "Via Garibaldi, 51, Cadoneghe", "reviews": [{"name": "places/ChIJewn6MAzQfkcRTieeKzsX_Oo/reviews/ChZDSUhNMG9nS0VJQ0FnSUM5clAtTUd3EAE", "relativePublishTimeDescription": "2 months ago", "rating": 1, "text": {"text": "Disappointing dishes\nGrilled fish \u20ac22 with a cuttlefish, a prawn and half a sea bass\nSpaghetti with clams \u20ac12, the flavor is only garlic\nMixed fried food \u20ac17, soft and invisible prawns\nCr\u00eapes \u20ac5 invisible icing sugar not to mention the presentation... better not to say anything else...\nYou contact the place and are told that the price is high and the dish is poor because it is delivered to you by Glovo\nNOT RECOMMENDED\u2026", "languageCode": "en-US"}, "originalText": {"text": "Piatti deludenti\nGrigliata di pesce 22\u20ac con una seppia un gambero e mezzo branzino\nSpaghetti alle vongole 12\u20ac il gusto \u00e8 solo di aglio\nFritto misto 17\u20ac molli e gamberetti invisibili\nCr\u00eapes 5\u20ac zucchero a velo invisibile per non parlare della presentazione\u2026meglio non aggiungere altro\u2026\nContatti il locale e ti viene detto che il prezzo alto e il piatto scarso perch\u00e9 ti viene consegnato da Glovo\nSCONSIGLIATISSIMO\u2026", "languageCode": "it"}, "authorAttribution": {"displayName": "Andrea De Luca", "uri": "https://www.google.com/maps/contrib/100205352962426801961/reviews", "photoUri": "https://lh3.googleusercontent.com/a/ACg8ocL78jTwm-30PALVnxwOeVrYgc94ogB9GMOiZwQPjmEIwRgrOw=s128-c0x00000000-cc-rp-mo"}, "publishTime": "2024-03-03T21:28:34Z"}, {"name": "places/ChIJewn6MAzQfkcRTieeKzsX_Oo/reviews/ChZDSUhNMG9nS0VJQ0FnSUNOcm9QQlF3EAE", "relativePublishTimeDescription": "4 months ago", "rating": 4, "text": {"text": "Birthday lunch for 60 years.\nWe were all satisfied.\nKindness and professionalism from the owners.\nClassic restaurant atmosphere, I would say excellent quality products. I recommend to everyone!!!", "languageCode": "en-US"}, "originalText": {"text": "Pranzo di Compleanno per i 60 anni.\nSiamo stati tutti soddisfatti.\nGentilezza e professionalit\u00e0 da parte del proprietari.\nAmbiente classico da trattoria, prodotti direi di ottima qualit\u00e0. Consiglio a tutti!!!", "languageCode": "it"}, "authorAttribution": {"displayName": "Nicole", "uri": "https://www.google.com/maps/contrib/102550657416929303726/reviews", "photoUri": "https://lh3.googleusercontent.com/a-/ALV-UjV5U3mKsJ5p37eqnyzvkE7xRM9NP-ondawDE0glMmj2QhvEzqR5=s128-c0x00000000-cc-rp-mo-ba5"}, "publishTime": "2024-01-14T17:10:34Z"}, {"name": "places/ChIJewn6MAzQfkcRTieeKzsX_Oo/reviews/ChdDSUhNMG9nS0VJQ0FnSURWX19xRjNRRRAB", "relativePublishTimeDescription": "5 months ago", "rating": 5, "text": {"text": "Simple, genuine and welcoming place. Very friendly and professional managers. Ideal for dinners with families and friends.... We come here often and it's always a pleasure to come back.", "languageCode": "en-US"}, "originalText": {"text": "Locale semplice, genuino ed accogliente. Gestori molto cordiali e professionali. Ideale per cene di famiglie e con amici.... Ci veniamo spesso ed \u00e8 sempre un piacere tornarci.", "languageCode": "it"}, "authorAttribution": {"displayName": "Silvano Toniutti", "uri": "https://www.google.com/maps/contrib/111017026005970159655/reviews", "photoUri": "https://lh3.googleusercontent.com/a/ACg8ocLDxl5XETBJeTAMtPtc28xdsTgOktqAsA0COEMuXAsTtnZpcA=s128-c0x00000000-cc-rp-mo"}, "publishTime": "2023-12-19T19:16:32Z"}, {"name": "places/ChIJewn6MAzQfkcRTieeKzsX_Oo/reviews/ChdDSUhNMG9nS0VJQ0FnSUNsanFTeW1RRRAB", "relativePublishTimeDescription": "6 months ago", "rating": 5, "text": {"text": "We went here for a small birthday celebration. Kind and attentive managers, good and not burnt pizza (just a little small), equally tasty first courses. Large room with some games for both children and adults. Advised!", "languageCode": "en-US"}, "originalText": {"text": "Siamo stati qui per una piccola festa di compleanno. Gestori gentili e premurosi, pizza buona e non bruciata (solo un po' piccola), primi altrettanto gustosi. Locale grande con alcuni giochi sia per piccoli che per grandi . Consigliato!", "languageCode": "it"}, "authorAttribution": {"displayName": "Massimo Previato", "uri": "https://www.google.com/maps/contrib/109026061045313972191/reviews", "photoUri": "https://lh3.googleusercontent.com/a-/ALV-UjVkEDd81HyZOoCUl4LzK14E8cAbLM408dx-PcjynmCIVYK-RTFW=s128-c0x00000000-cc-rp-mo-ba4"}, "publishTime": "2023-11-18T11:30:57Z"}, {"name": "places/ChIJewn6MAzQfkcRTieeKzsX_Oo/reviews/ChdDSUhNMG9nS0VJQ0FnSUNXek1yTmhRRRAB", "relativePublishTimeDescription": "2 years ago", "rating": 4, "text": {"text": "slightly old-fashioned but welcoming location.\ncourteous, smiling, helpful and prepared staff.\noptimal waiting time.\nwell-stocked and clean toilets.\ncheap price, very good pizzas.\nOverall, great experience. advised!", "languageCode": "en-US"}, "originalText": {"text": "location un po\u2019 all\u2019antica, ma accogliente.\npersonale cortese, sorridente, disponibile e preparato.\ntempo di attesa ottimale.\nservizi igienici ben forniti e puliti.\nprezzo economico, pizze molto buone.\nin complesso, ottima esperienza. consigliato!", "languageCode": "it"}, "authorAttribution": {"displayName": "FRANCESCA VECCHI", "uri": "https://www.google.com/maps/contrib/107253480257842537859/reviews", "photoUri": "https://lh3.googleusercontent.com/a/ACg8ocIek1Do0e2H39_B4x630aiZeJ9IrHHwINtRCiifQ1AnydEM0A=s128-c0x00000000-cc-rp-mo"}, "publishTime": "2022-02-19T19:36:58Z"}], "photos": [{"name": "places/ChIJewn6MAzQfkcRTieeKzsX_Oo/photos/AUGGfZmh2wDUaW6j4lWDNAc4ZxmkTMtr-lwIp4EX8oa3yZF5nXVlYLl60oR5ILLj4bjg-t3FN-8aUHcGVldAY3KgY9N7D_qJuLa8pKGJ2qDVAUmLt-z40P3sK4Eok0n5VuoxtCkDDjumHd_DeZFAItu0WldKXzU073O67E7f", "widthPx": 2560, "heightPx": 1536, "authorAttributions": [{"displayName": "stefano carraro", "uri": "//maps.google.com/maps/contrib/113354649984400313248", "photoUri": "//lh3.googleusercontent.com/a-/ALV-UjUjQ7iGFsOk0xX8HKLaFkbk0ZwE95e2NWH_K0L_4uvEVOC4ltg=s100-p-k-no-mo"}]}, {"name": "places/ChIJewn6MAzQfkcRTieeKzsX_Oo/photos/AUGGfZkfsT7jAqE6h-Hgy5c1nBNQWMsIMoe6pUwSQD0wy4cb3Aj6YIvq5d10WyzRZgT6-T97Nh-BIuuBcuZrWEgGhawLSKUchWCfClF41xPyQW38YKhKPMoBEvHa7ThlE6vwnZ0PqYhtE-RHjmNdMnEUOyNWOjNl8xyVVKyG", "widthPx": 3000, "heightPx": 4000, "authorAttributions": [{"displayName": "Dali Nm", "uri": "//maps.google.com/maps/contrib/116137785359798919762", "photoUri": "//lh3.googleusercontent.com/a/ACg8ocI_U6KImdmF_a5FPml3wfcP9Kqfd_5nYGOwglwptEHIrhBFEg=s100-p-k-no-mo"}]}, {"name": "places/ChIJewn6MAzQfkcRTieeKzsX_Oo/photos/AUGGfZnURzOZyM6smocUD1BYQhksi9xoVwUqyeQltZ8hjWJgdkqL56HEJ1Oqv9EwHnqGmY5YHX0fq7AIhU1KdCv2-JJp4g7-mYMavuHlHu9ho3DBxVhc7QvFAZordedjGEJuNf5YHT9xfZMHiRcwPlG-G7KpKVbUVkcpb5af", "widthPx": 4032, "heightPx": 3024, "authorAttributions": [{"displayName": "Mario Lunardi", "uri": "//maps.google.com/maps/contrib/100633106266457789507", "photoUri": "//lh3.googleusercontent.com/a-/ALV-UjUOUXuyKO56zufCwjSDu85dP2IHHvdyGvqzegAXurHfDwfilkU9=s100-p-k-no-mo"}]}, {"name": "places/ChIJewn6MAzQfkcRTieeKzsX_Oo/photos/AUGGfZmyFvPCY0h0jgXeyF94MDt6Q7O-pwr6Iwxxq_iOA7XHoAs4ufQnWQLQJ-Kld3FxoQl1GknM884obP9BJDca_5YvdhNRE8Oh3qkblHNm4gwoQiWIjQ6TwDtlIACNFHHiAp3fo1V7IQdC6cylLCSMYOgOljMCM18SHTlo", "widthPx": 3024, "heightPx": 4032, "authorAttributions": [{"displayName": "Aldo Tomat", "uri": "//maps.google.com/maps/contrib/106323760579722107511", "photoUri": "//lh3.googleusercontent.com/a/ACg8ocL_C9fA6SU3t0CdmT7puRm1s63t-YCmBiSpErHDqAwn7TWS-w=s100-p-k-no-mo"}]}, {"name": "places/ChIJewn6MAzQfkcRTieeKzsX_Oo/photos/AUGGfZlpJTGYwALD5ENUU5qHzQU8kg5Wqq4C8-7mih9HY_OqDdjATchlibFMM3zzIlFVo7FMSjtdLy5ILcmLR5dGXVO2UuoKuzgapbvN3Egkmt5LYogXy4xR7rU8JhVA32UP29GfrgdWlQnOU9lQX84mzyDcK8ToQBntKS0", "widthPx": 2322, "heightPx": 4128, "authorAttributions": [{"displayName": "carmen madalina lazar", "uri": "//maps.google.com/maps/contrib/104829668647871891470", "photoUri": "//lh3.googleusercontent.com/a-/ALV-UjXaKN10UH67_PmqD3kh9ZFoyCs8ovdsvRM6KD0EVw5CCxcIsGU=s100-p-k-no-mo"}]}, {"name": "places/ChIJewn6MAzQfkcRTieeKzsX_Oo/photos/AUGGfZnxcisYFAxD8mLjuUKvbX8XHaNskwzx3AUbTF7ZBvmAieT-ddCS9ofJSJ0eaAr3YQdJZfVFfHs5w67kRLjZpHtWWoUoolfRwrEECycsWXdZEAHZbU1OYi8cirfBjlv2c2bVyrShTm3Idi3KnZmc2d_jnXyEoSaTMZwI", "widthPx": 1536, "heightPx": 2560, "authorAttributions": [{"displayName": "stefano carraro", "uri": "//maps.google.com/maps/contrib/113354649984400313248", "photoUri": "//lh3.googleusercontent.com/a-/ALV-UjUjQ7iGFsOk0xX8HKLaFkbk0ZwE95e2NWH_K0L_4uvEVOC4ltg=s100-p-k-no-mo"}]}, {"name": "places/ChIJewn6MAzQfkcRTieeKzsX_Oo/photos/AUGGfZldyD2gk36yjLY1Y-rzrC73t--b8ffHPiP9HjhTy82s0xJu-6DhbINVxsJDSbElFFL-GhHOWamIGPCt0PQDi3SeXXgv6JV0g6oiZCuoscWwbf4pvy5b1DdmKtGH5uP_fVTgBQphG9lgU_pY6VYiz5YUiekAn14rK_g", "widthPx": 3264, "heightPx": 1840, "authorAttributions": [{"displayName": "Sara Aghi", "uri": "//maps.google.com/maps/contrib/109077758791169552574", "photoUri": "//lh3.googleusercontent.com/a/ACg8ocKNxFHmSiJDUwTvRysNt8zlOTfT96n5XN1fvzZaMOPyILNs=s100-p-k-no-mo"}]}, {"name": "places/ChIJewn6MAzQfkcRTieeKzsX_Oo/photos/AUGGfZlUTpp6drLgtIGAgo0jHdrrwRA7BMILR3xr9-hDxIzdjl7taZ98OLe9Opm_FmXurAdOX0y3pbB7vMDHjGt4wZfF1IbfU30byzzhYvwCFylaQpnpaiRqTdYtd9XrqyKI2UBKKmeX9TwzskNQqgHUw73yEe3mvNJYcOud", "widthPx": 2560, "heightPx": 1536, "authorAttributions": [{"displayName": "stefano carraro", "uri": "//maps.google.com/maps/contrib/113354649984400313248", "photoUri": "//lh3.googleusercontent.com/a-/ALV-UjUjQ7iGFsOk0xX8HKLaFkbk0ZwE95e2NWH_K0L_4uvEVOC4ltg=s100-p-k-no-mo"}]}, {"name": "places/ChIJewn6MAzQfkcRTieeKzsX_Oo/photos/AUGGfZmJ8K0L5wlHXseA_fRSivxiZubq6ARBSgU-xdlUExVb_uM9thtc2Gc4v-CXAnK8l5VAPxsrzCpHW3ylGoVU_oGXoZLRVXJkKIc3qAKI54NJMdox1gVw17BIuEAJyvrK1rPmjXI8dL57wN-n77cTUYaH4jUeTwkVRaq3", "widthPx": 4032, "heightPx": 3024, "authorAttributions": [{"displayName": "Vittorio Favretto", "uri": "//maps.google.com/maps/contrib/102133717951482257270", "photoUri": "//lh3.googleusercontent.com/a-/ALV-UjUXkVJeExppx-AXWQysvGnvBWkC_ikcbnQDNCsaNdCJybgyem9EXg=s100-p-k-no-mo"}]}, {"name": "places/ChIJewn6MAzQfkcRTieeKzsX_Oo/photos/AUGGfZmYPVwngbGo7FmUGodJyERHFuNvlBZL841HA8BYVKqJaNcdaNHGALLn3Fz9bdN-pbXlmGD5mMeOXkcMVDBacMT8CawsAGVl5brnl5ZzjqFpMgpwLghH4laZ2wHHFcXJnzw3C5WGZ_OT0Z2ZxmfERxy_1iIPIuFai9Zt", "widthPx": 3024, "heightPx": 4032, "authorAttributions": [{"displayName": "FRANCESCA VECCHI", "uri": "//maps.google.com/maps/contrib/107253480257842537859", "photoUri": "//lh3.googleusercontent.com/a/ACg8ocIek1Do0e2H39_B4x630aiZeJ9IrHHwINtRCiifQ1AnydEM0A=s100-p-k-no-mo"}]}], "outdoorSeating": true, "liveMusic": true, "menuForChildren": true, "servesDessert": true, "servesCoffee": true, "goodForChildren": true, "allowsDogs": true, "restroom": true, "goodForGroups": true, "goodForWatchingSports": true, "paymentOptions": {"acceptsCreditCards": true, "acceptsDebitCards": true, "acceptsCashOnly": false}, "parkingOptions": {"freeParkingLot": true, "freeStreetParking": true}, "accessibilityOptions": {"wheelchairAccessibleParking": true, "wheelchairAccessibleEntrance": true, "wheelchairAccessibleRestroom": true, "wheelchairAccessibleSeating": true}}